antbase/__init__.py
antbase/app/__init__.py
antbase/app/cli.py
antbase/base/__init__.py
antbase/base/auth.py
antbase/base/bc.py
antbase/base/db.py
antbase/base/drive.py
antbase/base/dt.py
antbase/base/gas.py
antbase/base/im.py
antbase/base/kp.py
antbase/base/log.py
antbase/base/she.py
antbase/base/tg.py
antbase/base/tg_web.py
antbase/bot/__init__.py
antbase/bot/actor.py
antbase/bot/goal.py
antbase/bot/job.py
antbase/bot/lot.py
antbase/bot/order.py
antbase/bot/part.py
antbase/bot/target.py
antbase/bot/task.py
antbase/chain/__init__.py
antbase/chain/chain.py
antbase/chain/frame.py
antbase/chain/key.py
antbase/chain/meta.py
antbase/chain/metadata.py
antbase/chain/r.py
antbase/chain/sdo.py
antbase/chain/sko.py
antbase/cli/__init__.py
antbase/cli/main.py
antbase/fonts/nunito/DESCRIPTION.en_us.html
antbase/fonts/nunito/METADATA.pb
antbase/fonts/nunito/Nunito-Italic[wght].ttf
antbase/fonts/nunito/Nunito[wght].ttf
antbase/fonts/nunito/OFL.txt
antbase/images/antLogo.jpg
antbase/type/__init__.py
antbase/type/command.py
antbase/type/entity.py
antbase/type/execution.py
antbase/type/finance.py
antbase/type/item.py
antbase/type/lot.py
antbase/type/order.py
antbase-0.1a13.dist-info/LICENSE
antbase-0.1a13.dist-info/METADATA
antbase-0.1a13.dist-info/WHEEL
antbase-0.1a13.dist-info/entry_points.txt
antbase-0.1a13.dist-info/top_level.txt
antbase-0.1a13.dist-info/RECORD
