Metadata-Version: 2.1
Name: antbase
Version: 0.1a13
Summary: Antbase package
Home-page: https://github.com/antdg/antbase
Author: Dmitrii Galkin
Author-email: dg@jart.co
Classifier: Programming Language :: Python :: 3
Classifier: License :: OSI Approved :: MIT License
Classifier: Operating System :: OS Independent
Requires-Python: >=3.11
License-File: LICENSE
Requires-Dist: requests
